pandastic/__init__.py
pandastic/pandastic_env.yaml
pandastic/actions/__init__.py
pandastic/actions/delete_actions.py
pandastic/actions/download_actions.py
pandastic/actions/filelist_actions.py
pandastic/actions/replicate_actions.py
pandastic/actions/update_actions.py
pandastic/actions/upload_actions.py
pandastic/cli/__init__.py
pandastic/cli/data_manager.py
pandastic/cli/task_manager.py
pandastic/utils/__init__.py
pandastic/utils/common.py
pandastic/utils/dataset_handlers.py
pandastic/utils/tools.py
pandastic/wip/pandastic_findpath.py
pandastic/wip/pandastic_is_ds_related_to_done_job.py
pandastic/wip/pandastic_monitor_rules.py
pandastic/wip/pandastic_rse_report.py
pandastic/wip/pandastic_tabulate_jobs.py
pandastic/wip/pandastic_upload.py
pandastic-0.0.2.dist-info/METADATA
pandastic-0.0.2.dist-info/WHEEL
pandastic-0.0.2.dist-info/entry_points.txt
pandastic-0.0.2.dist-info/top_level.txt
pandastic-0.0.2.dist-info/RECORD
