Metadata-Version: 2.1
Name: pandastic
Version: 0.0.2
Summary: A command line tool for manipulating PanDA tasks and rucio datasets
Author-email: Mohamed Aly <mohamed.aly@cern.ch>
Maintainer-email: Mohamed Aly <mohamed.aly@cern.ch>
Project-URL: homepage, https://github.com/MoAly98/pandastic/tree/main
Classifier: Development Status :: 3 - Alpha
Classifier: Intended Audience :: Science/Research
Classifier: Programming Language :: Python :: 3
Classifier: Natural Language :: English
Classifier: Topic :: Scientific/Engineering :: Physics
Classifier: Typing :: Typed
Requires-Python: >=3.10
Requires-Dist: panda-client>=1.5.41
Requires-Dist: pandas>=1.5.3
Requires-Dist: rucio-clients>=1.29.10
Requires-Dist: jsonschema>=3.2.0
Requires-Dist: numpy>=1.24.2
Requires-Dist: urllib3>=1.26.8
Requires-Dist: rucio>=35.0.0
